datapath.v
module datapath(
    input E, rst, clk,
    input LD_R1, LD_R2, LD_R3, LD_DR1, LD_DR2, LD_AC, LD_outr,
    input [2:0] sel_A, // Who can drive Bus 1 : R1 (000), R2 (001), R3 (010), AC (011), outr (100)
    input sel_B,// Who can drive Bus 2 : R2
    output reg [3:0] outr 
);

    reg [3:0] R1, R2, R3, AC, DR1, DR2;
    wire [3:0] B1, B2;
    wire [3:0] ALU_out = DR1 + DR2 ;

    assign B1 = (sel_A == 3'b000) ? R1 :
            (sel_A == 3'b001) ? R2 :
            (sel_A == 3'b010) ? R3 :
            (sel_A == 3'b011) ? AC :
            (sel_A == 3'b100) ? outr : 4'b0000 ;
    
    assign B2 = R2 ;


    always @(posedge clk) begin

        if (rst) begin
            R1 <= 4'b0000;
            R2 <= 4'b0000;
            R3 <= 4'b0000;
            DR1 <= 4'b0000;
            DR2 <= 4'b0000;
            AC <= 4'b0000;
            outr <= 4'b0000;
        end 
        if (E) begin
            outr[3:0] <= B1[3:0];
        end 
        else begin 
            // T0
            if (LD_DR1 == 1 && LD_DR2 == 1) begin
                DR1[3:0] <= B1[3:0]; 
                DR2[3:0] <= B2[3:0];
            end 

            // T1
            if (LD_R1 == 1 && LD_AC == 1) begin
                AC[3:0] <= ALU_out[3:0]; 

                R1[3:0] <= B1[3:0];
            end 
            
            // T2
            if (LD_R3 == 1) begin
                R3[3:0] <= B1[3:0];
            end 

            // T3
            if (LD_R2 == 1) begin
                R2[3:0] <= B1[3:0];
            end
        end 
    end

endmodule

control_unit.v
module cu(
    input E,
    input [1:0] T,
    output reg [2:0] sel_A, // Who can drive Bus 1 : R1 (000), R2 (001), R3 (010), AC (011), outr (100)
    output reg sel_B,// Who can drive Bus 2 : R2
    //Decide which registers get data from a bus 
    output reg LD_R1, LD_R2, LD_R3, LD_DR1, LD_DR2, LD_AC, LD_outr,
    // output reg [1:0] ALU,
    output reg sel_DR1, sel_DR2
);


    always @(*) begin

        // default values
        sel_A   = 3'b000;
        sel_B   = 1'b0;
        LD_R1   = 1'b0;
        LD_R2   = 1'b0;
        LD_R3   = 1'b0;
        LD_DR1  = 1'b0;
        LD_DR2  = 1'b0;
        LD_AC   = 1'b0;
        LD_outr = 1'b0;
        

        if (E == 1) begin

            sel_A[2:0] = 3'b010; // R3
            LD_outr = 1;

            sel_A   = 0;
            sel_B   = 0;
            LD_R1   = 0;
            LD_R2   = 0;
            LD_R3   = 0;
            LD_DR1  = 0;
            LD_DR2  = 0;
            LD_AC   = 0;

        end 
        else begin
            // T0
            if (T[1:0] == 2'b00) begin
                sel_A[2:0] = 3'b000; // R1
                sel_B = 1; // R2
                LD_DR1 = 1; 
                LD_DR2 = 1;
            end
            // T1
            else if (T[1:0] == 2'b01) begin
                sel_A[2:0] = 3'b001; // R2
                LD_R1 = 1; 
                LD_AC = 1;
            end 
            // T2
            else if (T[1:0] == 2'b10) begin
                sel_A[2:0] = 3'b011; // AC
                LD_R3 = 1;
            end
            // T3 
            else if (T[1:0] == 2'b11) begin
                sel_A[2:0] = 3'b010; // R3
                LD_R2 = 1;
            end 
        end 
    end 
endmodule

sequence_counter.v
module sequence_counter(
    //The inputs important for sequence counter
    input E, clk, rst,
    //At first, T is set to 0 (just a default thing)
    output reg [1:0] T
);

    reg E_prev;
    
    always @(posedge clk) begin

        //Everything is being reset to 0, even T 
        if (rst == 1) begin
            T[1:0] <= 2'b00;
            E_prev <= 1'b0;
        end 
        else begin
            if (E_prev == 1'b1 && E == 1'b0) begin
                T[1:0] <= 2'b00;              // restart cycle
            end
            //Stop where you are and show me the output at this moment
            //So T has to freeze
            else if (E == 1'b1) begin
                T <= T;    
            end
            //In normal operations, just keep increasing and wraping around T
            else begin
                if (T[1:0] == 2'b11) begin 
                //If you reached 3, start fresh from 0
                T[1:0] <= 2'b00;
                end
                else begin
                    //Otherwise, just keep increasing T on each clk
                    T[1:0] <= T[1:0] + 2'b01 ;
                end       
            end

            E_prev <= E;
        end
        
    end

endmodule

main.v
module main(
    input E,
    input clk,
    input rst,
    output [1:0] T,
    output LD_R1, LD_R2, LD_R3,
    output LD_DR1, LD_DR2, LD_AC, LD_outr,
    output [2:0] sel_A,
    output sel_B,
    // output [1:0] ALU,
    output [3:0] outr,
    output sel_DR1, sel_DR2
);

reg [1:0] T_reg;


sequence_counter sequence_inst(
    .E (E), .clk (clk), .rst (rst), .T (T)
); 
cu cu_inst(
    .E (E), .T (T),
    .sel_A (sel_A), 
    .sel_B (sel_B),
    .LD_R1 (LD_R1), .LD_R2 (LD_R2), .LD_R3 (LD_R3), .LD_DR1 (LD_DR1), .LD_DR2 (LD_DR2), .LD_AC (LD_AC), .LD_outr (LD_outr),
    // .ALU (ALU),
    .sel_DR1 (sel_DR1), 
    .sel_DR2 (sel_DR2) 
); 
datapath dp_inst(
    .E (E), .rst (rst), .clk (clk),
    .LD_R1 (LD_R1), .LD_R2 (LD_R2), .LD_R3 (LD_R3), .LD_DR1 (LD_DR1), .LD_DR2 (LD_DR2), .LD_AC (LD_AC), .LD_outr (LD_outr),
    .sel_A (sel_A), .sel_B (sel_B), .outr (outr)
);

endmodule;

tb_main.v
`timescale 1ns/1ps

module tb_main;

    // testbench signals
    reg clk;
    reg rst;
    reg E;

    // outputs from DUT
    wire [1:0] T;
    wire LD_R1, LD_R2, LD_R3;
    wire LD_DR1, LD_DR2, LD_AC, LD_outr;
    wire [2:0] sel_A;
    wire sel_B;
    // wire [1:0] ALU;
    wire [3:0] outr;
    wire sel_DR1, sel_DR2;

    // instantiate DUT
    main uut (
        .E(E),
        .clk(clk),
        .rst(rst),
        .T(T),
        .LD_R1(LD_R1), .LD_R2(LD_R2), .LD_R3(LD_R3),
        .LD_DR1(LD_DR1), .LD_DR2(LD_DR2), .LD_AC(LD_AC), .LD_outr(LD_outr),
        .sel_A(sel_A),
        .sel_B(sel_B),
        // .ALU(ALU),
        .outr(outr),
        .sel_DR1(sel_DR1), .sel_DR2(sel_DR2)
    );


    // clock generation: 10ns period
    always #5 clk = ~clk;

    initial begin
        // dump for GTKWave
        $dumpfile("main_wave.vcd");
        $dumpvars(0, tb_main);

        // init
        clk = 0;
        rst = 1;
        E   = 0;

        // Wait for 20ns, then do : rst = 0
        #20;
        rst = 0;

        uut.dp_inst.R1 = 4'd3;
        uut.dp_inst.R2 = 4'd5;

        #70;

        // freeze
        E = 1;
        #40;

        // restart
        E = 0;
        #60;

        $finish;
    end

endmodule

main_wave.vcd
$date
	Wed Dec 31 17:03:07 2025
$end
$version
	Icarus Verilog
$end
$timescale
	1ps
$end
$scope module tb_main $end
$var wire 1 ! sel_DR2 $end
$var wire 1 " sel_DR1 $end
$var wire 1 # sel_B $end
$var wire 3 $ sel_A [2:0] $end
$var wire 4 % outr [3:0] $end
$var wire 2 & T [1:0] $end
$var wire 1 ' LD_outr $end
$var wire 1 ( LD_R3 $end
$var wire 1 ) LD_R2 $end
$var wire 1 * LD_R1 $end
$var wire 1 + LD_DR2 $end
$var wire 1 , LD_DR1 $end
$var wire 1 - LD_AC $end
$var reg 1 . E $end
$var reg 1 / clk $end
$var reg 1 0 rst $end
$scope module uut $end
$var wire 1 . E $end
$var wire 1 / clk $end
$var wire 1 0 rst $end
$var wire 1 ! sel_DR2 $end
$var wire 1 " sel_DR1 $end
$var wire 1 # sel_B $end
$var wire 3 1 sel_A [2:0] $end
$var wire 4 2 outr [3:0] $end
$var wire 2 3 T [1:0] $end
$var wire 1 ' LD_outr $end
$var wire 1 ( LD_R3 $end
$var wire 1 ) LD_R2 $end
$var wire 1 * LD_R1 $end
$var wire 1 + LD_DR2 $end
$var wire 1 , LD_DR1 $end
$var wire 1 - LD_AC $end
$scope module cu_inst $end
$var wire 1 . E $end
$var wire 2 4 T [1:0] $end
$var reg 1 - LD_AC $end
$var reg 1 , LD_DR1 $end
$var reg 1 + LD_DR2 $end
$var reg 1 * LD_R1 $end
$var reg 1 ) LD_R2 $end
$var reg 1 ( LD_R3 $end
$var reg 1 ' LD_outr $end
$var reg 3 5 sel_A [2:0] $end
$var reg 1 # sel_B $end
$var reg 1 " sel_DR1 $end
$var reg 1 ! sel_DR2 $end
$upscope $end
$scope module dp_inst $end
$var wire 4 6 B2 [3:0] $end
$var wire 1 . E $end
$var wire 1 - LD_AC $end
$var wire 1 , LD_DR1 $end
$var wire 1 + LD_DR2 $end
$var wire 1 * LD_R1 $end
$var wire 1 ) LD_R2 $end
$var wire 1 ( LD_R3 $end
$var wire 1 ' LD_outr $end
$var wire 1 / clk $end
$var wire 1 0 rst $end
$var wire 3 7 sel_A [2:0] $end
$var wire 1 # sel_B $end
$var wire 4 8 B1 [3:0] $end
$var wire 4 9 ALU_out [3:0] $end
$var reg 4 : AC [3:0] $end
$var reg 4 ; DR1 [3:0] $end
$var reg 4 < DR2 [3:0] $end
$var reg 4 = R1 [3:0] $end
$var reg 4 > R2 [3:0] $end
$var reg 4 ? R3 [3:0] $end
$var reg 4 @ outr [3:0] $end
$upscope $end
$scope module sequence_inst $end
$var wire 1 . E $end
$var wire 1 / clk $end
$var wire 1 0 rst $end
$var reg 1 A E_prev $end
$var reg 2 B T [1:0] $end
$upscope $end
$upscope $end
$upscope $end
$enddefinitions $end
$comment Show the parameter values. $end
$dumpall
$end
#0
$dumpvars
bx B
xA
bx @
bx ?
bx >
bx =
bx <
bx ;
bx :
bx 9
bx 8
b0 7
bx 6
b0 5
bx 4
bx 3
bx 2
b0 1
10
0/
0.
0-
0,
0+
0*
0)
0(
0'
bx &
bx %
b0 $
0#
x"
x!
$end
#5000
1+
1,
1#
b0 8
0A
b0 &
b0 3
b0 4
b0 B
b0 %
b0 2
b0 @
b0 :
b0 9
b0 <
b0 ;
b0 ?
b0 6
b0 >
b0 =
1/
#10000
0/
#15000
1/
#20000
b11 8
0/
b101 6
b101 >
b11 =
00
#25000
b101 8
1-
1*
b1 $
b1 1
b1 5
b1 7
0+
0,
0#
b1 &
b1 3
b1 4
b1 B
b101 <
b1000 9
b11 ;
1/
#30000
0/
#35000
b1000 8
1(
0-
0*
b11 $
b11 1
b11 5
b11 7
b101 =
b1000 :
b10 &
b10 3
b10 4
b10 B
1/
#40000
0/
#45000
1)
0(
b10 $
b10 1
b10 5
b10 7
b11 &
b11 3
b11 4
b11 B
b1000 ?
1/
#50000
0/
#55000
b101 8
1+
1,
1#
0)
b0 $
b0 1
b0 5
b0 7
b1000 6
b1000 >
b0 &
b0 3
b0 4
b0 B
1/
#60000
0/
#65000
b1000 8
1-
1*
b1 $
b1 1
b1 5
b1 7
0+
0,
0#
b1 &
b1 3
b1 4
b1 B
b1000 <
b1101 9
b101 ;
1/
#70000
0/
#75000
b1101 8
1(
0-
0*
b11 $
b11 1
b11 5
b11 7
b1000 =
b1101 :
b10 &
b10 3
b10 4
b10 B
1/
#80000
0/
#85000
1)
0(
b10 $
b10 1
b10 5
b10 7
b11 &
b11 3
b11 4
b11 B
b1101 ?
1/
#90000
b1000 8
1'
0)
b0 $
b0 1
b0 5
b0 7
0/
1.
#95000
b1000 %
b1000 2
b1000 @
1A
1/
#100000
0/
#105000
1/
#110000
0/
#115000
1/
#120000
0/
#125000
1/
#130000
b1101 8
1)
b10 $
b10 1
b10 5
b10 7
0'
0/
0.
#135000
b1000 8
1+
1,
1#
0)
b0 $
b0 1
b0 5
b0 7
b1101 6
b1101 >
0A
b0 &
b0 3
b0 4
b0 B
1/
#140000
0/
#145000
b1101 8
1-
1*
b1 $
b1 1
b1 5
b1 7
0+
0,
0#
b1 &
b1 3
b1 4
b1 B
b1101 <
b101 9
b1000 ;
1/
#150000
0/
#155000
b101 8
1(
0-
0*
b11 $
b11 1
b11 5
b11 7
b1101 =
b101 :
b10 &
b10 3
b10 4
b10 B
1/
#160000
0/
#165000
1)
0(
b10 $
b10 1
b10 5
b10 7
b11 &
b11 3
b11 4
b11 B
b101 ?
1/
#170000
0/
#175000
b1101 8
1+
1,
1#
0)
b0 $
b0 1
b0 5
b0 7
b101 6
b101 >
b0 &
b0 3
b0 4
b0 B
1/
#180000
0/
#185000
b101 8
1-
1*
b1 $
b1 1
b1 5
b1 7
0+
0,
0#
b1 &
b1 3
b1 4
b1 B
b101 <
b10 9
b1101 ;
1/
